README.md
setup.py
heatmapper/__init__.py
heatmapper/heatmapper.py
heatmapper/test.py
heatmapper/utils.py
heatmapper.egg-info/PKG-INFO
heatmapper.egg-info/SOURCES.txt
heatmapper.egg-info/dependency_links.txt
heatmapper.egg-info/requires.txt
heatmapper.egg-info/top_level.txt