Metadata-Version: 1.0
Name: heatmapper
Version: 1.0.0
Summary: Python library for creating heatmap
Home-page: https://github.com/luckcul/heatmapper
Author: luckcul
Author-email: tyfdream@gmail.com
License: MIT Licence
Keywords: heatmap
Platform: any
